graphqlite/__init__.py
graphqlite/_platform.py
graphqlite/connection.py
graphqlite/graphqlite.dylib
graphqlite/manager.py
graphqlite/utils.py
graphqlite/algorithms/__init__.py
graphqlite/algorithms/_parsing.py
graphqlite/algorithms/centrality.py
graphqlite/algorithms/community.py
graphqlite/algorithms/components.py
graphqlite/algorithms/export.py
graphqlite/algorithms/paths.py
graphqlite/algorithms/similarity.py
graphqlite/algorithms/traversal.py
graphqlite/graph/__init__.py
graphqlite/graph/_base.py
graphqlite/graph/batch.py
graphqlite/graph/bulk.py
graphqlite/graph/edges.py
graphqlite/graph/nodes.py
graphqlite/graph/queries.py
graphqlite-0.3.2.dist-info/METADATA
graphqlite-0.3.2.dist-info/WHEEL
graphqlite-0.3.2.dist-info/top_level.txt
graphqlite-0.3.2.dist-info/RECORD
