Metadata-Version: 2.4
Name: graphqlite
Version: 0.3.2
Summary: SQLite extension for graph queries using Cypher
Author: GraphQLite Contributors
License: MIT
Project-URL: Homepage, https://github.com/colliery-io/graphqlite
Project-URL: Repository, https://github.com/colliery-io/graphqlite
Keywords: sqlite,graph,cypher,database
Classifier: Development Status :: 4 - Beta
Classifier: Intended Audience :: Developers
Classifier: License :: OSI Approved :: MIT License
Classifier: Programming Language :: Python :: 3
Classifier: Programming Language :: Python :: 3.8
Classifier: Programming Language :: Python :: 3.9
Classifier: Programming Language :: Python :: 3.10
Classifier: Programming Language :: Python :: 3.11
Classifier: Programming Language :: Python :: 3.12
Classifier: Topic :: Database
Requires-Python: >=3.8
Provides-Extra: dev
Requires-Dist: pytest>=7.0; extra == "dev"
Requires-Dist: pytest-cov; extra == "dev"
Provides-Extra: leiden
Requires-Dist: graspologic>=3.0; extra == "leiden"
Provides-Extra: rustworkx
Requires-Dist: rustworkx>=0.13; extra == "rustworkx"
